contraqctor/__init__.py
contraqctor/_typing.py
contraqctor/contract/__init__.py
contraqctor/contract/base.py
contraqctor/contract/camera.py
contraqctor/contract/csv.py
contraqctor/contract/harp.py
contraqctor/contract/json.py
contraqctor/contract/mux.py
contraqctor/contract/text.py
contraqctor/contract/utils.py
contraqctor/py.typed
contraqctor/qc/__init__.py
contraqctor/qc/_context_extensions.py
contraqctor/qc/base.py
contraqctor/qc/camera.py
contraqctor/qc/contract.py
contraqctor/qc/csv.py
contraqctor/qc/harp/__init__.py
contraqctor/qc/harp/environment_sensor.py
contraqctor/qc/harp/harp_device.py
contraqctor/qc/harp/lickety_split.py
contraqctor/qc/harp/sniff_detector.py
contraqctor/qc/harp/treadmill.py
contraqctor/qc/reporters.py
contraqctor/qc/serializers.py
contraqctor/qc/templates/report.html
contraqctor-0.5.3.dist-info/WHEEL
contraqctor-0.5.3.dist-info/METADATA
contraqctor-0.5.3.dist-info/RECORD
