Metadata-Version: 2.4
Name: contraqctor
Version: 0.5.3
Summary: A library for managing data contracts and quality control in behavioral datasets.
Author: Bruno Cruz
Author-email: Bruno Cruz <bruno.cruz@alleninstitute.org>
License-Expression: MIT
Classifier: Programming Language :: Python :: 3.11
Classifier: Operating System :: Microsoft :: Windows
Requires-Dist: aind-behavior-services
Requires-Dist: harp-python
Requires-Dist: jinja2
Requires-Dist: matplotlib
Requires-Dist: numpy
Requires-Dist: pandas
Requires-Dist: pydantic
Requires-Dist: pyyaml
Requires-Dist: requests
Requires-Dist: rich
Requires-Dist: semver
Requires-Dist: scipy
Requires-Dist: opencv-python
Requires-Python: >=3.11
Project-URL: Changelog, https://github.com/AllenNeuralDynamics/contraqctor/releases
Project-URL: Documentation, https://allenneuraldynamics.github.io/contraqctor/
Project-URL: Issues, https://github.com/AllenNeuralDynamics/contraqctor/issues
Project-URL: Repository, https://github.com/AllenNeuralDynamics/contraqctor/
